LICENSE
symtool/__init__.py
symtool/disasm.py
symtool/main.py
symtool/symtool.py
symtool-0.0.6.dist-info/entry_points.txt
symtool-0.0.6.dist-info/LICENSE
symtool-0.0.6.dist-info/WHEEL
symtool-0.0.6.dist-info/METADATA
symtool-0.0.6.dist-info/RECORD
