Metadata-Version: 2.1
Name: symtool
Version: 0.0.6
Summary: A tool for interacting with your SYM-1 microcomputer
Home-page: https://github.com/larsks/symtool
License: GPLv3
Author: Lars Kellogg-Stedman
Author-email: lars@oddbit.com
Requires-Python: >=3.7,<4.0
Classifier: License :: Other/Proprietary License
Classifier: Programming Language :: Python :: 3
Classifier: Programming Language :: Python :: 3.7
Classifier: Programming Language :: Python :: 3.8
Classifier: Programming Language :: Python :: 3.9
Requires-Dist: click (>=7.1.2,<8.0.0)
Requires-Dist: hexdump (>=3.3,<4.0)
Requires-Dist: pyserial (>=3.5,<4.0)
Project-URL: Repository, https://github.com/larsks/symtool
